example/__init__.py
example/config.py
example/manage.py
example/settings.py
example/web.py
pt/__init__.py
pt/consumer.py
pt/tweet.py
pt/version.py
pulsar_twitter-0.1.0.dist-info/DESCRIPTION.rst
pulsar_twitter-0.1.0.dist-info/LICENSE.txt
pulsar_twitter-0.1.0.dist-info/METADATA
pulsar_twitter-0.1.0.dist-info/RECORD
pulsar_twitter-0.1.0.dist-info/WHEEL
pulsar_twitter-0.1.0.dist-info/metadata.json
pulsar_twitter-0.1.0.dist-info/top_level.txt
