Metadata-Version: 2.0
Name: pulsar-twitter
Version: 0.1.0
Summary: Twitter consumer for pulsar queue
Home-page: https://github.com/quantmind/pulsar-twitter
Author: Luca Sbardella
Author-email: luca@quantmind.com
License: BSD
Platform: UNKNOWN
Classifier: Development Status :: 3 - Alpha
Classifier: Environment :: Web Environment
Classifier: Intended Audience :: Developers
Classifier: License :: OSI Approved :: BSD License
Classifier: Operating System :: OS Independent
Classifier: Programming Language :: Python
Classifier: Programming Language :: Python :: 3.5
Classifier: Programming Language :: Python :: 3.6
Classifier: Topic :: Utilities
Requires-Dist: oauthlib
Requires-Dist: pulsar-queue
